rs_client/__init__.py
rs_client/auxip_client.py
rs_client/cadip_client.py
rs_client/rs_client.py
rs_client/stac_client.py
rs_common/__init__.py
rs_common/config.py
rs_common/logging.py
rs_common/opentelemetry.py
rs_common/serialization.py
rs_common/utils.py
rs_workflows/__init__.py
rs_workflows/config/dpr_config_template.yaml
rs_workflows/example.py
rs_workflows/s1_l0.py
rs_workflows/staging.py
rs_client_libraries-99.99.dist-info/LICENSE
rs_client_libraries-99.99.dist-info/METADATA
rs_client_libraries-99.99.dist-info/WHEEL
rs_client_libraries-99.99.dist-info/RECORD
