Metadata-Version: 2.1
Name: rs-client-libraries
Version: 99.99
Summary: Copernicus Sentinel rs-client library and processing workflows.
Home-page: https://home.rs-python.eu/
License: Apache-2.0
Keywords: stac,copernicus,sentinel,processing
Author: ESA under contract with Airbus and CS
Author-email: ops_coprs@airbus.com
Requires-Python: >=3.11,<4.0
Classifier: Development Status :: 3 - Alpha
Classifier: Framework :: OpenTelemetry
Classifier: Intended Audience :: Developers
Classifier: Intended Audience :: Science/Research
Classifier: License :: OSI Approved :: Apache Software License
Classifier: Programming Language :: Python :: 3
Classifier: Programming Language :: Python :: 3.11
Classifier: Programming Language :: Python :: 3.12
Classifier: Programming Language :: Python :: 3.13
Classifier: Topic :: Scientific/Engineering :: Image Processing
Classifier: Topic :: Software Development :: Libraries :: Python Modules
Requires-Dist: cachetools (>=5.3.3,<6.0.0)
Requires-Dist: numpy (==2.1.2)
Requires-Dist: opentelemetry-distro (>=0.48b0,<0.49)
Requires-Dist: opentelemetry-exporter-otlp (>=1.27.0,<2.0.0)
Requires-Dist: opentelemetry-instrumentation-aws-lambda (>=0.48b0,<0.49)
Requires-Dist: opentelemetry-test-utils (>=0.48b0,<0.49)
Requires-Dist: prefect (>=2.14.21,<3.0.0)
Requires-Dist: prefect-dask (>=0.2.6,<0.3.0)
Requires-Dist: pystac (>=1.10.1,<2.0.0)
Requires-Dist: pystac-client (>=0.8.1,<0.9.0)
Requires-Dist: python-dateutil (>=2.9.0.post0,<3.0.0)
Requires-Dist: python-logging-loki (>=0.3.1,<0.4.0)
Requires-Dist: shapely (>=2.0.6,<3.0.0)
Requires-Dist: starlette (>=0.38.4,<0.39.0)
Project-URL: Documentation, https://home.rs-python.eu/rs-documentation/rs-client-libraries/docs/doc/
Project-URL: Repository, https://github.com/RS-PYTHON/rs-client-libraries
